eythos/.DS_Store
eythos/__init__.py
eythos/art_parsing.py
eythos/output/.DS_Store
eythos/output/output.csv
eythos/output/output1.csv
eythos/output/output（1）.csv
eythos/test.xlsx
eythos-0.1.2.dist-info/METADATA
eythos-0.1.2.dist-info/WHEEL
eythos-0.1.2.dist-info/RECORD
